<?xml version="1.0" encoding="UTF-8"?>
<Components xmlns:xsi="http://www.w3.org/2001/XMLSchema-instance" xsi:noNamespaceSchemaLocation="Components.xsd">
	<TableKey table="PERSON" key="JUNIT" />
	<Heading SECTION="WEBC01" color="red" size="H1" emphasis="INFO" alignment="LEFT">
		<Title>Title</Title>
		<Collection />
		<Text>Contact Information</Text>
		<SubText>Including address</SubText>
	</Heading>
	<FieldSet SECTION="WEBC01" enabled="true">
		<Collection>
			<FormGroup>
				<Collection>
					<FormLabel KEY="FL00_1" isHtml="false">
						<Text>first name:</Text>
					</FormLabel>
					<Input KEY="FV00_1" type="TEXT">
						<Value>Hello</Value>
					</Input>
				</Collection>
			</FormGroup>
			<FormGroup>
				<Collection>
					<FormLabel KEY="FL00_2" isHtml="false">
						<Text>last name:</Text>
					</FormLabel>
					<Input KEY="FV00_2" type="TEXT">
					</Input>
				</Collection>
			</FormGroup>
			<FormGroup>
				<Collection>
					<FormLabel KEY="FL00_3" isHtml="false">
						<Text>middle name:</Text>
					</FormLabel>
					<TextBox KEY="FV00_3">
						<Value>textbox</Value>
					</TextBox>
				</Collection>
			</FormGroup>
			<FormGroup>
				<Collection>
					<FormLabel KEY="FL00_12" isHtml="false">
						<Text>Field4:</Text>
					</FormLabel>
					<ListBox KEY="FV00_12" multipleSelect="false">
						<Lookup loc="TABLE" params="GENDER,UNKNOWN" />
					</ListBox>
				</Collection>
			</FormGroup>
			<FormGroup>
				<Collection>
					<FormLabel KEY="FL00_13" isHtml="false">
						<Text>Field4:</Text>
					</FormLabel>
					<FlexTable KEY="FV00_13" cols="2" maxrows="4" width="100%" headingSize="H5">
						<Title>Title</Title>
						<Headers>
							<string>Type</string>
							<string>Street 1</string>
							<string>Street 2</string>
							<string>City</string>
							<string>State</string>
							<string>Zip</string>
						</Headers>
					</FlexTable>
				</Collection>
			</FormGroup>
		</Collection>
	</FieldSet>
	<Icon SECTION="WEBL01" pull="LEFT" type="AMAZON" size="LARGE" border="true" spin="false" pulse="false" inverse="false">
		<Title>Title</Title>
	</Icon>
	<Badge SECTION="WEBR01">
		<Title>Title</Title>
		<Text>Text</Text>
	</Badge>
</Components>